README.md
setup.cfg
setup.py
StudioPulse/__init__.py
StudioPulse/cli.py
StudioPulse/debug.py
StudioPulse/event_stream.py
StudioPulse/job_settings.py
StudioPulse.egg-info/PKG-INFO
StudioPulse.egg-info/SOURCES.txt
StudioPulse.egg-info/dependency_links.txt
StudioPulse.egg-info/entry_points.txt
StudioPulse.egg-info/not-zip-safe
StudioPulse.egg-info/requires.txt
StudioPulse.egg-info/top_level.txt
StudioPulse/app/__init__.py
StudioPulse/app/api.py
StudioPulse/app/config.py
StudioPulse/app/mixin.py
StudioPulse/app/swagger.py
StudioPulse/app/blueprints/__init__.py
StudioPulse/app/blueprints/assets/__init__.py
StudioPulse/app/blueprints/assets/resources.py
StudioPulse/app/blueprints/auth/__init__.py
StudioPulse/app/blueprints/auth/resources.py
StudioPulse/app/blueprints/breakdown/__init__.py
StudioPulse/app/blueprints/breakdown/resources.py
StudioPulse/app/blueprints/chats/__init__.py
StudioPulse/app/blueprints/chats/resources.py
StudioPulse/app/blueprints/comments/__init__.py
StudioPulse/app/blueprints/comments/resources.py
StudioPulse/app/blueprints/concepts/__init__.py
StudioPulse/app/blueprints/concepts/resources.py
StudioPulse/app/blueprints/crud/__init__.py
StudioPulse/app/blueprints/crud/asset_instance.py
StudioPulse/app/blueprints/crud/attachment_file.py
StudioPulse/app/blueprints/crud/base.py
StudioPulse/app/blueprints/crud/chat.py
StudioPulse/app/blueprints/crud/chat_message.py
StudioPulse/app/blueprints/crud/comments.py
StudioPulse/app/blueprints/crud/custom_action.py
StudioPulse/app/blueprints/crud/day_off.py
StudioPulse/app/blueprints/crud/department.py
StudioPulse/app/blueprints/crud/entity.py
StudioPulse/app/blueprints/crud/entity_link.py
StudioPulse/app/blueprints/crud/entity_type.py
StudioPulse/app/blueprints/crud/event.py
StudioPulse/app/blueprints/crud/file_status.py
StudioPulse/app/blueprints/crud/metadata_descriptor.py
StudioPulse/app/blueprints/crud/milestone.py
StudioPulse/app/blueprints/crud/news.py
StudioPulse/app/blueprints/crud/notification.py
StudioPulse/app/blueprints/crud/organisation.py
StudioPulse/app/blueprints/crud/output_file.py
StudioPulse/app/blueprints/crud/output_type.py
StudioPulse/app/blueprints/crud/person.py
StudioPulse/app/blueprints/crud/playlist.py
